<BugCollection analysisTimestamp="1488490994705" release="" sequence="0" timestamp="1486177968000" version="3.0.1">
  <BugInstance abbrev="SECSQLIJDBC" category="SECURITY" priority="1" rank="10" type="SQL_INJECTION_JDBC">
    <Class classname="org.owasp.benchmark.testcode.BenchmarkTest02186">
      <SourceLine classname="org.owasp.benchmark.testcode.BenchmarkTest02186" end="68" sourcefile="BenchmarkTest02186.java" sourcepath="org/owasp/benchmark/testcode/BenchmarkTest02186.java" start="30" />
    </Class>
    <Method classname="org.owasp.benchmark.testcode.BenchmarkTest02186" isStatic="false" name="doPost" signature="(Ljavax/servlet/http/HttpServletRequest;Ljavax/servlet/http/HttpServletResponse;)V">
      <SourceLine classname="org.owasp.benchmark.testcode.BenchmarkTest02186" end="68" endBytecode="433" sourcefile="BenchmarkTest02186.java" sourcepath="org/owasp/benchmark/testcode/BenchmarkTest02186.java" start="42" startBytecode="0" />
    </Method>
    <SourceLine classname="org.owasp.benchmark.testcode.BenchmarkTest02186" end="64" endBytecode="128" sourcefile="BenchmarkTest02186.java" sourcepath="org/owasp/benchmark/testcode/BenchmarkTest02186.java" start="64" startBytecode="128" />
    <String role="Sink method" value="Statement.execute(...)" />
    <String role="Instruction Handle" value=" 128: invokeinterface[185](5) 22" />
    <String role="Parameter Taint" value="T7 {toString()}" />
    <String role="Taint Frame" value="[U0[2] {[?]+[?]}U1[1] {[?]+[?]}U2[0] {[?]+[?]}T3 {[&quot;&quot;]+[nextElement()]}T4 {[getHeaderNames()]+[getHeaderNames()]}T5 {add()}T6 {get()}T7 {toString()}U8 {getSqlStatement()}|U8 {getSqlStatement()}T7 {toString()}]" />
    <String role="Method Bytecode" value="Code(max_stack = 3, max_locals = 9, code_length = 150) 0:    ldc  &quot;&quot; (3) 2:    astore_3 3:    aload_1 4:    invokeinterface javax.servlet.http.HttpServletRequest.getHeaderNames ()Ljava/util/Enumeration; (4) 1 0 9:    astore  %4 11:   aload  %4 13:   invokeinterface java.util.Enumeration.hasMoreElements ()Z (5) 1 0 18:   ifeq  #32 21:   aload  %4 23:   invokeinterface java.util.Enumeration.nextElement ()Ljava/lang/Object; (6) 1 0 28:   checkcast  &lt;java.lang.String&gt; (7) 31:   astore_3 32:   new  &lt;java.util.ArrayList&gt; (8) 35:   dup 36:   invokespecial java.util.ArrayList.&lt;init&gt; ()V (9) 39:   astore  %5 41:   aload  %5 43:   ldc  &quot;safe&quot; (10) 45:   invokeinterface java.util.List.add (Ljava/lang/Object;)Z (11) 2 0 50:   pop 51:   aload  %5 53:   aload_3 54:   invokeinterface java.util.List.add (Ljava/lang/Object;)Z (11) 2 0 59:   pop 60:   aload  %5 62:   ldc  &quot;moresafe&quot; (12) 64:   invokeinterface java.util.List.add (Ljava/lang/Object;)Z (11) 2 0 69:   pop 70:   aload  %5 72:   iconst_0 73:   invokeinterface java.util.List.remove (I)Ljava/lang/Object; (13) 2 0 78:   pop 79:   aload  %5 81:   iconst_1 82:   invokeinterface java.util.List.get (I)Ljava/lang/Object; (14) 2 0 87:   checkcast  &lt;java.lang.String&gt; (7) 90:   astore  %6 92:   new  &lt;java.lang.StringBuilder&gt; (15) 95:   dup 96:   invokespecial java.lang.StringBuilder.&lt;init&gt; ()V (16) 99:   ldc  &quot;SELECT * from USERS where USERNAME='foo' and PASSWORD='&quot; (17) 101:  invokevirtual java.lang.StringBuilder.append (Ljava/lang/String;)Ljava/lang/StringBuilder; (18) 104:  aload  %6 106:  invokevirtual java.lang.StringBuilder.append (Ljava/lang/String;)Ljava/lang/StringBuilder; (18) 109:  ldc  &quot;'&quot; (19) 111:  invokevirtual java.lang.StringBuilder.append (Ljava/lang/String;)Ljava/lang/StringBuilder; (18) 114:  invokevirtual java.lang.StringBuilder.toString ()Ljava/lang/String; (20) 117:  astore  %7 119:  invokestatic org.owasp.benchmark.helpers.DatabaseHelper.getSqlStatement ()Ljava/sql/Statement; (21) 122:  astore  %8 124:  aload  %8 126:  aload  %7 128:  invokeinterface java.sql.Statement.execute (Ljava/lang/String;)Z (22) 2 0 133:  pop 134:  goto  #149 137:  astore  %8 139:  new  &lt;javax.servlet.ServletException&gt; (24) 142:  dup 143:  aload  %8 145:  invokespecial javax.servlet.ServletException.&lt;init&gt; (Ljava/lang/Throwable;)V (25) 148:  athrow 149:  return  Exception handler(s) =  From To Handler Type 119 134 137 java.sql.SQLException(23)  Attribute(s) =  LineNumber(0, 42), LineNumber(3, 43), LineNumber(11, 44), LineNumber(21, 45),  LineNumber(32, 49), LineNumber(41, 50), LineNumber(51, 51), LineNumber(60, 52),  LineNumber(70, 54), LineNumber(79, 56), LineNumber(92, 60), LineNumber(119, 63),  LineNumber(124, 64), LineNumber(134, 67), LineNumber(137, 65), LineNumber(139, 66),  LineNumber(149, 68) LocalVariable(start_pc = 124, length = 10, index = 8:java.sql.Statement statement) LocalVariable(start_pc = 139, length = 10, index = 8:java.sql.SQLException e) LocalVariable(start_pc = 0, length = 150, index = 0:org.owasp.benchmark.testcode.BenchmarkTest02186 this) LocalVariable(start_pc = 0, length = 150, index = 1:javax.servlet.http.HttpServletRequest request) LocalVariable(start_pc = 0, length = 150, index = 2:javax.servlet.http.HttpServletResponse response) LocalVariable(start_pc = 3, length = 147, index = 3:String param) LocalVariable(start_pc = 11, length = 139, index = 4:java.util.Enumeration headerNames) LocalVariable(start_pc = 41, length = 109, index = 5:java.util.List valuesList) LocalVariable(start_pc = 92, length = 58, index = 6:String bar) LocalVariable(start_pc = 119, length = 31, index = 7:String sql) LocalVariable(start_pc = 11, length = 139, index = 4:java.util.Enumeration&lt;Ljava.lang.String headerNames) LocalVariable(start_pc = 41, length = 109, index = 5:java.util.List&lt;Ljava.lang.String valuesList) StackMapTable((APPEND 2, offset delta=32, locals={(type=Object, class=java.lang.String), (type=Object, class=java.util.Enumeration)}), (FULL, offset delta=104, locals={(type=Object, class=org.owasp.benchmark.testcode.BenchmarkTest02186), (type=Object, class=javax.servlet.http.HttpServletRequest), (type=Object, class=javax.servlet.http.HttpServletResponse), (type=Object, class=java.lang.String), (type=Object, class=java.util.Enumeration), (type=Object, class=java.util.List), (type=Object, class=java.lang.String), (type=Object, class=java.lang.String)}, stack items={(type=Object, class=java.sql.SQLException)}), (SAME, offset delta=11)) " />
    <SourceLine classname="org.owasp.benchmark.testcode.BenchmarkTest02186" end="43" endBytecode="4" sourcefile="BenchmarkTest02186.java" sourcepath="org/owasp/benchmark/testcode/BenchmarkTest02186.java" start="43" startBytecode="4" />
    <SourceLine classname="org.owasp.benchmark.testcode.BenchmarkTest02186" end="45" endBytecode="23" sourcefile="BenchmarkTest02186.java" sourcepath="org/owasp/benchmark/testcode/BenchmarkTest02186.java" start="45" startBytecode="23" />
    <SourceLine classname="org.owasp.benchmark.testcode.BenchmarkTest02186" end="51" endBytecode="54" sourcefile="BenchmarkTest02186.java" sourcepath="org/owasp/benchmark/testcode/BenchmarkTest02186.java" start="51" startBytecode="54" />
    <SourceLine classname="org.owasp.benchmark.testcode.BenchmarkTest02186" end="52" endBytecode="64" sourcefile="BenchmarkTest02186.java" sourcepath="org/owasp/benchmark/testcode/BenchmarkTest02186.java" start="52" startBytecode="64" />
    <SourceLine classname="org.owasp.benchmark.testcode.BenchmarkTest02186" end="56" endBytecode="82" sourcefile="BenchmarkTest02186.java" sourcepath="org/owasp/benchmark/testcode/BenchmarkTest02186.java" start="56" startBytecode="82" />
    <SourceLine classname="org.owasp.benchmark.testcode.BenchmarkTest02186" end="60" endBytecode="106" sourcefile="BenchmarkTest02186.java" sourcepath="org/owasp/benchmark/testcode/BenchmarkTest02186.java" start="60" startBytecode="106" />
  </BugInstance>
  </BugCollection>