<BugCollection analysisTimestamp="1488493465260" release="" sequence="0" timestamp="1486177968000" version="3.0.1">
  <BugInstance abbrev="SECSQLIJDBC" category="SECURITY" priority="1" rank="10" type="SQL_INJECTION_JDBC">
    <Class classname="org.owasp.benchmark.testcode.BenchmarkTest03441">
      <SourceLine classname="org.owasp.benchmark.testcode.BenchmarkTest03441" end="62" sourcefile="BenchmarkTest03441.java" sourcepath="org/owasp/benchmark/testcode/BenchmarkTest03441.java" start="30" />
    </Class>
    <Method classname="org.owasp.benchmark.testcode.BenchmarkTest03441" isStatic="false" name="doPost" signature="(Ljavax/servlet/http/HttpServletRequest;Ljavax/servlet/http/HttpServletResponse;)V">
      <SourceLine classname="org.owasp.benchmark.testcode.BenchmarkTest03441" end="62" endBytecode="390" sourcefile="BenchmarkTest03441.java" sourcepath="org/owasp/benchmark/testcode/BenchmarkTest03441.java" start="42" startBytecode="0" />
    </Method>
    <SourceLine classname="org.owasp.benchmark.testcode.BenchmarkTest03441" end="58" endBytecode="125" sourcefile="BenchmarkTest03441.java" sourcepath="org/owasp/benchmark/testcode/BenchmarkTest03441.java" start="58" startBytecode="125" />
    <String role="Sink method" value="Statement.execute(...)" />
    <String role="Instruction Handle" value=" 125: invokeinterface[185](5) 24" />
    <String role="Parameter Taint" value="T6 {toString()}" />
    <String role="Taint Frame" value="[U0[2] {?}U1[1] {?}U2[0] {?}T3 {getParameter()}T4 {get()}T5 {put()}T6 {toString()}U7 {getSqlStatement()}|U7 {getSqlStatement()}T6 {toString()}U {?}]" />
    <String role="Method Bytecode" value="Code(max_stack = 6, max_locals = 8, code_length = 147) 0:    aload_1 1:    ldc  &quot;foo&quot; (3) 3:    invokeinterface javax.servlet.http.HttpServletRequest.getParameter (Ljava/lang/String;)Ljava/lang/String; (4) 2 0 8:    astore_3 9:    ldc  &quot;safe!&quot; (5) 11:   astore  %4 13:   new  &lt;java.util.HashMap&gt; (6) 16:   dup 17:   invokespecial java.util.HashMap.&lt;init&gt; ()V (7) 20:   astore  %5 22:   aload  %5 24:   ldc  &quot;keyA-14249&quot; (8) 26:   ldc  &quot;a_Value&quot; (9) 28:   invokevirtual java.util.HashMap.put (Ljava/lang/Object;Ljava/lang/Object;)Ljava/lang/Object; (10) 31:   pop 32:   aload  %5 34:   ldc  &quot;keyB-14249&quot; (11) 36:   aload_3 37:   invokevirtual java.lang.String.toString ()Ljava/lang/String; (12) 40:   invokevirtual java.util.HashMap.put (Ljava/lang/Object;Ljava/lang/Object;)Ljava/lang/Object; (10) 43:   pop 44:   aload  %5 46:   ldc  &quot;keyC&quot; (13) 48:   ldc  &quot;another_Value&quot; (14) 50:   invokevirtual java.util.HashMap.put (Ljava/lang/Object;Ljava/lang/Object;)Ljava/lang/Object; (10) 53:   pop 54:   aload  %5 56:   ldc  &quot;keyB-14249&quot; (11) 58:   invokevirtual java.util.HashMap.get (Ljava/lang/Object;)Ljava/lang/Object; (15) 61:   checkcast  &lt;java.lang.String&gt; (16) 64:   astore  %4 66:   aload  %5 68:   ldc  &quot;keyA-14249&quot; (8) 70:   invokevirtual java.util.HashMap.get (Ljava/lang/Object;)Ljava/lang/Object; (15) 73:   checkcast  &lt;java.lang.String&gt; (16) 76:   astore  %4 78:   new  &lt;java.lang.StringBuilder&gt; (17) 81:   dup 82:   invokespecial java.lang.StringBuilder.&lt;init&gt; ()V (18) 85:   ldc  &quot;SELECT * from USERS where USERNAME='foo' and PASSWORD='&quot; (19) 87:   invokevirtual java.lang.StringBuilder.append (Ljava/lang/String;)Ljava/lang/StringBuilder; (20) 90:   aload  %4 92:   invokevirtual java.lang.StringBuilder.append (Ljava/lang/String;)Ljava/lang/StringBuilder; (20) 95:   ldc  &quot;'&quot; (21) 97:   invokevirtual java.lang.StringBuilder.append (Ljava/lang/String;)Ljava/lang/StringBuilder; (20) 100:  invokevirtual java.lang.StringBuilder.toString ()Ljava/lang/String; (22) 103:  astore  %6 105:  invokestatic org.owasp.benchmark.helpers.DatabaseHelper.getSqlStatement ()Ljava/sql/Statement; (23) 108:  astore  %7 110:  aload  %7 112:  aload  %6 114:  iconst_2 115:  newarray  &lt;int&gt; 117:  dup 118:  iconst_0 119:  iconst_1 120:  iastore 121:  dup 122:  iconst_1 123:  iconst_2 124:  iastore 125:  invokeinterface java.sql.Statement.execute (Ljava/lang/String;[I)Z (24) 3 0 130:  pop 131:  goto  #146 134:  astore  %7 136:  new  &lt;javax.servlet.ServletException&gt; (26) 139:  dup 140:  aload  %7 142:  invokespecial javax.servlet.ServletException.&lt;init&gt; (Ljava/lang/Throwable;)V (27) 145:  athrow 146:  return  Exception handler(s) =  From To Handler Type 105 131 134 java.sql.SQLException(25)  Attribute(s) =  LineNumber(0, 42), LineNumber(9, 45), LineNumber(13, 46), LineNumber(22, 47),  LineNumber(32, 48), LineNumber(44, 49), LineNumber(54, 50), LineNumber(66, 51),  LineNumber(78, 54), LineNumber(105, 57), LineNumber(110, 58), LineNumber(131, 61),  LineNumber(134, 59), LineNumber(136, 60), LineNumber(146, 62) LocalVariable(start_pc = 110, length = 21, index = 7:java.sql.Statement statement) LocalVariable(start_pc = 136, length = 10, index = 7:java.sql.SQLException e) LocalVariable(start_pc = 0, length = 147, index = 0:org.owasp.benchmark.testcode.BenchmarkTest03441 this) LocalVariable(start_pc = 0, length = 147, index = 1:javax.servlet.http.HttpServletRequest request) LocalVariable(start_pc = 0, length = 147, index = 2:javax.servlet.http.HttpServletResponse response) LocalVariable(start_pc = 9, length = 138, index = 3:String param) LocalVariable(start_pc = 13, length = 134, index = 4:String bar) LocalVariable(start_pc = 22, length = 125, index = 5:java.util.HashMap map14249) LocalVariable(start_pc = 105, length = 42, index = 6:String sql) LocalVariable(start_pc = 22, length = 125, index = 5:java.util.HashMap&lt;Ljava.lang.String map14249) StackMapTable((FULL, offset delta=134, locals={(type=Object, class=org.owasp.benchmark.testcode.BenchmarkTest03441), (type=Object, class=javax.servlet.http.HttpServletRequest), (type=Object, class=javax.servlet.http.HttpServletResponse), (type=Object, class=java.lang.String), (type=Object, class=java.lang.String), (type=Object, class=java.util.HashMap), (type=Object, class=java.lang.String)}, stack items={(type=Object, class=java.sql.SQLException)}), (SAME, offset delta=11)) " />
    <SourceLine classname="org.owasp.benchmark.testcode.BenchmarkTest03441" end="42" endBytecode="3" sourcefile="BenchmarkTest03441.java" sourcepath="org/owasp/benchmark/testcode/BenchmarkTest03441.java" start="42" startBytecode="3" />
    <SourceLine classname="org.owasp.benchmark.testcode.BenchmarkTest03441" end="48" endBytecode="37" sourcefile="BenchmarkTest03441.java" sourcepath="org/owasp/benchmark/testcode/BenchmarkTest03441.java" start="48" startBytecode="37" />
    <SourceLine classname="org.owasp.benchmark.testcode.BenchmarkTest03441" end="49" endBytecode="50" sourcefile="BenchmarkTest03441.java" sourcepath="org/owasp/benchmark/testcode/BenchmarkTest03441.java" start="49" startBytecode="50" />
    <SourceLine classname="org.owasp.benchmark.testcode.BenchmarkTest03441" end="51" endBytecode="70" sourcefile="BenchmarkTest03441.java" sourcepath="org/owasp/benchmark/testcode/BenchmarkTest03441.java" start="51" startBytecode="70" />
    <SourceLine classname="org.owasp.benchmark.testcode.BenchmarkTest03441" end="54" endBytecode="97" sourcefile="BenchmarkTest03441.java" sourcepath="org/owasp/benchmark/testcode/BenchmarkTest03441.java" start="54" startBytecode="97" />
  </BugInstance>
  </BugCollection>