<BugCollection analysisTimestamp="1488545931683" release="" sequence="0" timestamp="1486177968000" version="3.0.1">
  <BugInstance abbrev="SECSQLIJDBC" category="SECURITY" priority="2" rank="12" type="SQL_INJECTION_JDBC">
    <Class classname="org.owasp.benchmark.testcode.BenchmarkTest04021">
      <SourceLine classname="org.owasp.benchmark.testcode.BenchmarkTest04021" end="64" sourcefile="BenchmarkTest04021.java" sourcepath="org/owasp/benchmark/testcode/BenchmarkTest04021.java" start="30" />
    </Class>
    <Method classname="org.owasp.benchmark.testcode.BenchmarkTest04021" isStatic="false" name="doPost" signature="(Ljavax/servlet/http/HttpServletRequest;Ljavax/servlet/http/HttpServletResponse;)V">
      <SourceLine classname="org.owasp.benchmark.testcode.BenchmarkTest04021" end="64" endBytecode="395" sourcefile="BenchmarkTest04021.java" sourcepath="org/owasp/benchmark/testcode/BenchmarkTest04021.java" start="42" startBytecode="0" />
    </Method>
    <SourceLine classname="org.owasp.benchmark.testcode.BenchmarkTest04021" end="58" endBytecode="93" sourcefile="BenchmarkTest04021.java" sourcepath="org/owasp/benchmark/testcode/BenchmarkTest04021.java" start="58" startBytecode="93" />
    <String role="Sink method" value="Connection.prepareCall(...)" />
    <String role="Instruction Handle" value="  93: invokeinterface[185](5) 19" />
    <String role="Parameter Taint" value="U7 {toString()}" />
    <String role="Taint Frame" value="[U0[2] {[?]+[?]}U1[1] {[?]+[?]}U2[0] {[?]+[?]}T3 {[getParameterMap()]+[getParameterMap()]}T4 {[&quot;&quot;]+[get()]}U5 {createThing()}U6 {doSomething()}U7 {toString()}U8 {getSqlConnection()}U9 {[?]+[?]}|U8 {getSqlConnection()}U7 {toString()}S {?}S {?}]" />
    <String role="Method Bytecode" value="Code(max_stack = 4, max_locals = 10, code_length = 124) 0:    aload_1 1:    invokeinterface javax.servlet.http.HttpServletRequest.getParameterMap ()Ljava/util/Map; (3) 1 0 6:    astore_3 7:    ldc  &quot;&quot; (4) 9:    astore  %4 11:   aload_3 12:   invokeinterface java.util.Map.isEmpty ()Z (5) 1 0 17:   ifne  #35 20:   aload_3 21:   ldc  &quot;foo&quot; (6) 23:   invokeinterface java.util.Map.get (Ljava/lang/Object;)Ljava/lang/Object; (7) 2 0 28:   checkcast  &lt;[Ljava.lang.String;&gt; (8) 31:   iconst_0 32:   aaload 33:   astore  %4 35:   invokestatic org.owasp.benchmark.helpers.ThingFactory.createThing ()Lorg/owasp/benchmark/helpers/ThingInterface; (9) 38:   astore  %5 40:   aload  %5 42:   aload  %4 44:   invokeinterface org.owasp.benchmark.helpers.ThingInterface.doSomething (Ljava/lang/String;)Ljava/lang/String; (10) 2 0 49:   astore  %6 51:   new  &lt;java.lang.StringBuilder&gt; (11) 54:   dup 55:   invokespecial java.lang.StringBuilder.&lt;init&gt; ()V (12) 58:   ldc  &quot;{call verifyUserPassword('foo','&quot; (13) 60:   invokevirtual java.lang.StringBuilder.append (Ljava/lang/String;)Ljava/lang/StringBuilder; (14) 63:   aload  %6 65:   invokevirtual java.lang.StringBuilder.append (Ljava/lang/String;)Ljava/lang/StringBuilder; (14) 68:   ldc  &quot;')}&quot; (15) 70:   invokevirtual java.lang.StringBuilder.append (Ljava/lang/String;)Ljava/lang/StringBuilder; (14) 73:   invokevirtual java.lang.StringBuilder.toString ()Ljava/lang/String; (16) 76:   astore  %7 78:   invokestatic org.owasp.benchmark.helpers.DatabaseHelper.getSqlConnection ()Ljava/sql/Connection; (17) 81:   astore  %8 83:   aload  %8 85:   aload  %7 87:   sipush  1003 90:   sipush  1007 93:   invokeinterface java.sql.Connection.prepareCall (Ljava/lang/String;II)Ljava/sql/CallableStatement; (19) 4 0 98:   astore  %9 100:  aload  %9 102:  invokeinterface java.sql.CallableStatement.execute ()Z (20) 1 0 107:  pop 108:  goto  #123 111:  astore  %8 113:  new  &lt;javax.servlet.ServletException&gt; (22) 116:  dup 117:  aload  %8 119:  invokespecial javax.servlet.ServletException.&lt;init&gt; (Ljava/lang/Throwable;)V (23) 122:  athrow 123:  return  Exception handler(s) =  From To Handler Type 78 108 111 java.sql.SQLException(21)  Attribute(s) =  LineNumber(0, 42), LineNumber(7, 43), LineNumber(11, 44), LineNumber(20, 45),  LineNumber(35, 50), LineNumber(40, 51), LineNumber(51, 54), LineNumber(78, 57),  LineNumber(83, 58), LineNumber(100, 60), LineNumber(108, 63), LineNumber(111, 61),  LineNumber(113, 62), LineNumber(123, 64) LocalVariable(start_pc = 83, length = 25, index = 8:java.sql.Connection connection) LocalVariable(start_pc = 100, length = 8, index = 9:java.sql.CallableStatement statement) LocalVariable(start_pc = 113, length = 10, index = 8:java.sql.SQLException e) LocalVariable(start_pc = 0, length = 124, index = 0:org.owasp.benchmark.testcode.BenchmarkTest04021 this) LocalVariable(start_pc = 0, length = 124, index = 1:javax.servlet.http.HttpServletRequest request) LocalVariable(start_pc = 0, length = 124, index = 2:javax.servlet.http.HttpServletResponse response) LocalVariable(start_pc = 7, length = 117, index = 3:java.util.Map map) LocalVariable(start_pc = 11, length = 113, index = 4:String param) LocalVariable(start_pc = 40, length = 84, index = 5:org.owasp.benchmark.helpers.ThingInterface thing) LocalVariable(start_pc = 51, length = 73, index = 6:String bar) LocalVariable(start_pc = 78, length = 46, index = 7:String sql) LocalVariable(start_pc = 7, length = 117, index = 3:java.util.Map&lt;Ljava.lang.String map) StackMapTable((APPEND 2, offset delta=35, locals={(type=Object, class=java.util.Map), (type=Object, class=java.lang.String)}), (FULL, offset delta=75, locals={(type=Object, class=org.owasp.benchmark.testcode.BenchmarkTest04021), (type=Object, class=javax.servlet.http.HttpServletRequest), (type=Object, class=javax.servlet.http.HttpServletResponse), (type=Object, class=java.util.Map), (type=Object, class=java.lang.String), (type=Object, class=org.owasp.benchmark.helpers.ThingInterface), (type=Object, class=java.lang.String), (type=Object, class=java.lang.String)}, stack items={(type=Object, class=java.sql.SQLException)}), (SAME, offset delta=11)) " />
    <SourceLine classname="org.owasp.benchmark.testcode.BenchmarkTest04021" end="51" endBytecode="44" sourcefile="BenchmarkTest04021.java" sourcepath="org/owasp/benchmark/testcode/BenchmarkTest04021.java" start="51" startBytecode="44" />
    <SourceLine classname="org.owasp.benchmark.testcode.BenchmarkTest04021" end="54" endBytecode="73" sourcefile="BenchmarkTest04021.java" sourcepath="org/owasp/benchmark/testcode/BenchmarkTest04021.java" start="54" startBytecode="73" />
  </BugInstance>
  </BugCollection>